medical_waveforms/__init__.py
medical_waveforms/data/example_arterial_pressure_waveform.npy
medical_waveforms/features/__init__.py
medical_waveforms/features/cycles.py
medical_waveforms/features/diffs.py
medical_waveforms/features/waveform.py
medical_waveforms/quality.py
medical_waveforms/synthetic.py
medical_waveforms/utils.py
medical_waveforms/waveforms.py
medical_waveforms-0.1.5.dist-info/METADATA
medical_waveforms-0.1.5.dist-info/WHEEL
medical_waveforms-0.1.5.dist-info/RECORD
